_dummy_kraken_common/__init__.py
kraken_common-0.32.1.dist-info/METADATA
kraken_common-0.32.1.dist-info/WHEEL
kraken_common-0.32.1.dist-info/RECORD
