Metadata-Version: 2.1
Name: kraken-common
Version: 0.32.1
Summary: 
License: MIT
Author: Niklas Rosenstein
Author-email: rosensteinniklas@gmail.com
Classifier: License :: OSI Approved :: MIT License
Classifier: Programming Language :: Python :: 2
Classifier: Programming Language :: Python :: 2.7
Classifier: Programming Language :: Python :: 3
Classifier: Programming Language :: Python :: 3.4
Classifier: Programming Language :: Python :: 3.5
Classifier: Programming Language :: Python :: 3.6
Classifier: Programming Language :: Python :: 3.7
Classifier: Programming Language :: Python :: 3.8
Classifier: Programming Language :: Python :: 3.9
Classifier: Programming Language :: Python :: 3.10
Classifier: Programming Language :: Python :: 3.11
Classifier: Programming Language :: Python :: 3.12
Requires-Dist: kraken-build (==0.32.1)
Project-URL: Bug Tracker, https://github.com/kraken-build/kraken-build/issues
Project-URL: Documentation, https://kraken-build.github.io/kraken-build/
Project-URL: Homepage, https://kraken-build.github.io/kraken-build/
Project-URL: Repository, https://github.com/kraken-build/kraken-build/
